channel/__init__.py
channel/additive_noise_functions.py
channel/pulse_shaping.py
rx/__init__.py
rx/checker.py
rx/ctle_model.py
rx/decoding.py
rx/demapping.py
rx/lock_pattern.py
rx/slicer.py
rx/symbol2bin.py
tx/__init__.py
tx/bin2symbol.py
tx/coding.py
tx/mapping.py
tx/prbs_generator.py
tx/prbs_iterator.py
CommDspy-0.1.0.dist-info/LICENSE
CommDspy-0.1.0.dist-info/METADATA
CommDspy-0.1.0.dist-info/WHEEL
CommDspy-0.1.0.dist-info/top_level.txt
CommDspy-0.1.0.dist-info/RECORD
