Metadata-Version: 2.1
Name: CommDspy
Version: 0.1.0
Summary: This package holds implementations for some Communication DSP methodology I found useful and informative
Home-page: https://github.com/TomerGeva/CommDspy
Author: Tomer Geva
Author-email: tomerg777@gmail.com
License: UNKNOWN
Platform: UNKNOWN
Classifier: Programming Language :: Python :: 3
Classifier: License :: OSI Approved :: GNU Affero General Public License v3 or later (AGPLv3+)
Classifier: Operating System :: OS Independent
Requires-Python: >=3.6
License-File: LICENSE
